setup.cfg
setup.py
itab/__init__.py
itab/files.py
itab/reader.py
itab/schema.py
itab/writer.py
itab.egg-info/PKG-INFO
itab.egg-info/SOURCES.txt
itab.egg-info/dependency_links.txt
itab.egg-info/entry_points.txt
itab.egg-info/requires.txt
itab.egg-info/top_level.txt
itab/utils/__init__.py
itab/utils/check.py
itab/utils/help.py
tests/__init__.py
tests/writer.py