Metadata-Version: 1.1
Name: itab
Version: 0.4.0
Summary: Python tab files parsing and validating schema tools.
Home-page: https://github.com/bbglab/itab
Author: Jordi Deu-Pons
Author-email: jordi@jordeu.net
License: Apache License 2
Download-URL: https://github.com/bbglab/itab/archive/0.4.0.tar.gz
Platform: UNKNOWN
